CHANGES.txt
MANIFEST.in
README.txt
requirements.txt
setup.py
docs/design.txt
docs/install.txt
docs/notes.txt
points_assignment/__init__.py
points_assignment/settings.py
points_assignment/test_settings.py
points_assignment/urls.py
points_assignment/wsgi.py
stock_tweets.egg-info/PKG-INFO
stock_tweets.egg-info/SOURCES.txt
stock_tweets.egg-info/dependency_links.txt
stock_tweets.egg-info/not-zip-safe
stock_tweets.egg-info/requires.txt
stock_tweets.egg-info/top_level.txt
stocktweets/__init__.py
stocktweets/constants.py
stocktweets/forms.py
stocktweets/models.py
stocktweets/tests.py
stocktweets/urls.py
stocktweets/utils.py
stocktweets/views.py
templates/about.html
templates/base.html
templates/stocktweets/index.html