Metadata-Version: 1.0
Name: stock-tweets
Version: 0.1.0
Summary: Display stock and Tweet information
Home-page: http://pypi.python.org/pypi/stock-tweets/
Author: Harry Kim
Author-email: hkim85@gmail.com
License: LICENSE.txt
Platform: UNKNOWN
